{"cameraMode":{"drawMode":0,"name":"Shaded","section":"Shading Mode"},"sceneLighting":true,"audioPlay":false,"sceneViewState":{"m_AlwaysRefresh":false,"showFog":true,"showSkybox":true,"showFlares":true,"showImageEffects":true,"showParticleSystems":true,"showVisualEffectGraphs":true,"m_FxEnabled":true},"in2DMode":false,"pivot":{"x":13.512055397033692,"y":13.426878929138184,"z":-8.820962905883789},"rotation":{"x":0.2922578454017639,"y":0.6352527737617493,"z":-0.6565713286399841,"w":0.2827715575695038},"size":10.32064151763916,"orthographic":true}